{
  "$schema": "https://developer.microsoft.com/json-schemas/spfx-build/package-solution.schema.json",
  "solution": {
    "name": "asset-deployment-client-side-solution",
    "id": "3146ab7f-c50d-4752-a1a0-5d8deadc5c07",
    "version": "1.0.0.0",
    "includeClientSideAssets": true,
    "isDomainIsolated": false,
    "developer": {
      "name": "",
      "websiteUrl": "",
      "privacyUrl": "",
      "termsOfUseUrl": "",
      "mpnId": ""
    }
  },
  "paths": {
    "zippedPackage": "solution/asset-deployment.sppkg"
  }
}
